pusnowlib/__init__.py
pusnowlib/dj_bus/__init__.py
pusnowlib/kaist_bus/__init__.py
pusnowlib/kaist_food/__init__.py
pusnowlib/kaist_food/__main__.py
pusnowlib/unsafe_ssl.py
pusnowlib-0.1.1.dist-info/LICENSE
pusnowlib-0.1.1.dist-info/WHEEL
pusnowlib-0.1.1.dist-info/METADATA
pusnowlib-0.1.1.dist-info/RECORD
